noip_api_pkg/__init__.py
noip_api_pkg/noip_api.py
noip_api_CodeGuy3-0.0.1.dist-info/LICENCE
noip_api_CodeGuy3-0.0.1.dist-info/METADATA
noip_api_CodeGuy3-0.0.1.dist-info/WHEEL
noip_api_CodeGuy3-0.0.1.dist-info/top_level.txt
noip_api_CodeGuy3-0.0.1.dist-info/RECORD
