Metadata-Version: 2.1
Name: noip-api-CodeGuy3
Version: 0.0.1
Summary: A small noip api
Home-page: https://github.com/CodeGuy3/noip_api
Author: CodeGuy3
Author-email: kiko.smire@gmail.com
License: UNKNOWN
Platform: UNKNOWN
Classifier: Programming Language :: Python :: 3
Classifier: License :: OSI Approved :: MIT License
Classifier: Operating System :: OS Independent
Requires-Python: >=3.6
